pypi_wayback.py
pypi_wayback-0.2.2.dist-info/LICENSE
pypi_wayback-0.2.2.dist-info/METADATA
pypi_wayback-0.2.2.dist-info/WHEEL
pypi_wayback-0.2.2.dist-info/entry_points.txt
pypi_wayback-0.2.2.dist-info/RECORD
