Metadata-Version: 2.3
Name: pypi-wayback
Version: 0.2.2
Summary: 🕰️ Access any PyPI package’s history
Author: Alexander Kovrigin
Author-email: alexander.kovrigin@jetbrains.com
Requires-Python: >=3.10,<4.0
Classifier: Programming Language :: Python :: 3
Classifier: Programming Language :: Python :: 3.10
Classifier: Programming Language :: Python :: 3.11
Classifier: Programming Language :: Python :: 3.12
Classifier: Programming Language :: Python :: 3.13
Requires-Dist: beautifulsoup4 (>=4.12.3,<5.0.0)
Requires-Dist: flask (>=3.0.3,<4.0.0)
Requires-Dist: gunicorn (>=23.0.0,<24.0.0)
Requires-Dist: requests (>=2.32.3,<3.0.0)
